swagger_client/__init__.py
swagger_client/api_client.py
swagger_client/configuration.py
swagger_client/rest.py
swagger_client/api/__init__.py
swagger_client/api/matchdata_api.py
swagger_client/models/__init__.py
swagger_client/models/bl_table_team.py
swagger_client/models/global_result_info.py
swagger_client/models/goal.py
swagger_client/models/goal_getter.py
swagger_client/models/group.py
swagger_client/models/league.py
swagger_client/models/location.py
swagger_client/models/match.py
swagger_client/models/match_result.py
swagger_client/models/result_info.py
swagger_client/models/sport.py
swagger_client/models/team.py
openligadb_python_client-1.0.7.dist-info/LICENSE
openligadb_python_client-1.0.7.dist-info/METADATA
openligadb_python_client-1.0.7.dist-info/WHEEL
openligadb_python_client-1.0.7.dist-info/top_level.txt
openligadb_python_client-1.0.7.dist-info/RECORD
