Metadata-Version: 2.1
Name: openligadb_python_client
Version: 1.0.7
Summary: OpenLigaDB-API
Home-page: 
Author-email: 
Keywords: Swagger,OpenLigaDB-API
License-File: LICENSE
Requires-Dist: urllib3>=1.15
Requires-Dist: six>=1.10
Requires-Dist: certifi
Requires-Dist: python-dateutil
